[
    {
        "chunk_id": "Maudon_MAU_SO_V_5-PHU_LUC_V-268-2025-ND-CP_chunk_0001",
        "doc_id": "Maudon_MAU_SO_V_5-PHU_LUC_V-268-2025-ND-CP",
        "text": "Mẫu số V.5\n\nCỘNG HÒA XÃ HỘI CHỦ NGHĨA VIỆT NAM\nĐộc lập - Tự do - Hạnh phúc\n---------------\n\nĐƠN ĐỀ NGHỊ CẤP THAY ĐỔI NỘI DUNG/CẤP LẠI\nGIẤY CHỨNG NHẬN DOANH NGHIỆP KHOA HỌC VÀ CÔNG NGHỆ\n\nKính gửi: ………………………………\n\nI. THÔNG TIN DOANH NGHIỆP\n\n1. Tên doanh nghiệp:\n\n- Tên doanh nghiệp viết bằng tiếng Việt: ………………………………\n\n- Tên doanh nghiệp viết bằng tiếng nước ngoài (nếu có): ………………………………\n\n- Tên doanh nghiệp viết tắt (nếu có):\n\n2. Trụ sở chính:\n\n- Địa chỉ: ………………………………………………………………\n\n- Điện thoại: ……………………………… Fax: ………………………………\n\n- Email: ………………………………………………………………\n\n- Website: ………………………………………………………………\n\n3. Người đại diện theo pháp luật của doanh nghiệp:\n\n- Họ và tên: ………………………………Chức vụ: ………………………………\n\n- Căn cước công dân: số ………………..do ………..cấp ngày ... tháng ... năm……….\n\n- Điện thoại: ………………………………Email: ………………………………\n\n- Hộ khẩu thường trú: ………………………………………………………………\n\n- Chỗ ở hiện nay: ………………………………………………………………\n\n4. Giấy chứng nhận đăng ký doanh nghiệp:\n\n- Số …….ngày …..tháng ……năm ………., do ……………………cấp.",
        "metadata": {
            "chunk_index": 1,
            "total_chunks": 4,
            "prev_chunk_id": null,
            "next_chunk_id": "Maudon_MAU_SO_V_5-PHU_LUC_V-268-2025-ND-CP_chunk_0002",
            "char_count": 998,
            "source_file": "Maudon/MAU SO V.5-PHU LUC V-268-2025-ND-CP.doc",
            "file_name": "MAU SO V.5-PHU LUC V-268-2025-ND-CP.doc",
            "folder": "Maudon",
            "original_extension": ".doc",
            "cleaned_at": "2026-05-21T04:47:59",
            "chunked_at": "2026-05-21T21:52:04"
        }
    },
    {
        "chunk_id": "Maudon_MAU_SO_V_5-PHU_LUC_V-268-2025-ND-CP_chunk_0002",
        "doc_id": "Maudon_MAU_SO_V_5-PHU_LUC_V-268-2025-ND-CP",
        "text": "………………………………\n\n- Hộ khẩu thường trú: ………………………………………………………………\n\n- Chỗ ở hiện nay: ………………………………………………………………\n\n4. Giấy chứng nhận đăng ký doanh nghiệp:\n\n- Số …….ngày …..tháng ……năm ………., do ……………………cấp.\n\n- Loại hình doanh nghiệp: ………………………………………………………………\n\n5. Giấy chứng nhận doanh nghiệp khoa học và công nghệ của doanh nghiệp:\n\n- Cấp lần đầu số: ………………………………ngày………………………………\n\n- Cấp lại lần thứ ………………………………ngày………………………………\n\nII. DOANH NGHIỆP ĐỀ NGHỊ CẤP THAY ĐỔI NỘI DUNG GIẤY CHỨNG NHẬN DOANH NGHIỆP KHOA HỌC VÀ CÔNG NGHỆ\n\n1. Lý do thay đổi nội dung Giấy chứng nhận doanh nghiệp khoa học và công nghệ: ………………………………………………………………\n\n………………………………………………………………………………………………\n\n2. Doanh nghiệp đề nghị thay đổi các nội dung sau trên Giấy chứng nhận doanh nghiệp khoa học và công nghệ: ………………………………………………………………\n\n3. Trường hợp doanh nghiệp khoa học và công nghệ bổ sung Danh mục sản phẩm trên Giấy chứng nhận, doanh nghiệp kê khai các nội dung sau:",
        "metadata": {
            "chunk_index": 2,
            "total_chunks": 4,
            "prev_chunk_id": "Maudon_MAU_SO_V_5-PHU_LUC_V-268-2025-ND-CP_chunk_0001",
            "next_chunk_id": "Maudon_MAU_SO_V_5-PHU_LUC_V-268-2025-ND-CP_chunk_0003",
            "char_count": 930,
            "source_file": "Maudon/MAU SO V.5-PHU LUC V-268-2025-ND-CP.doc",
            "file_name": "MAU SO V.5-PHU LUC V-268-2025-ND-CP.doc",
            "folder": "Maudon",
            "original_extension": ".doc",
            "cleaned_at": "2026-05-21T04:47:59",
            "chunked_at": "2026-05-21T21:52:04"
        }
    },
    {
        "chunk_id": "Maudon_MAU_SO_V_5-PHU_LUC_V-268-2025-ND-CP_chunk_0003",
        "doc_id": "Maudon_MAU_SO_V_5-PHU_LUC_V-268-2025-ND-CP",
        "text": "doanh nghiệp khoa học và công nghệ: ………………………………………………………………\n\n3. Trường hợp doanh nghiệp khoa học và công nghệ bổ sung Danh mục sản phẩm trên Giấy chứng nhận, doanh nghiệp kê khai các nội dung sau:\n\na) Thông tin về kết quả nghiên cứu khoa học, phát triển công nghệ và đổi mới sáng tạo:\n\n- Tên kết quả: ………………………………………………………………\n\n- Nguồn gốc tài chính: ………………………………………………………………\n\n- Nguồn gốc hình thành (tự nghiên cứu/nhận chuyển giao): ………………………………\n\n- Văn bản công nhận: ………………………………………………………………\n\nb) Danh mục các sản phẩm khoa học, công nghệ và đổi mới sáng tạo bổ sung:…………………\n\nIII. DOANH NGHIỆP ĐỀ NGHỊ CẤP LẠI GIẤY CHỨNG NHẬN DOANH NGHIỆP KHOA HỌC VÀ CÔNG NGHỆ\n\nLý do đề nghị cấp lại Giấy chứng nhận doanh nghiệp khoa học và công nghệ:\n\n………………………………………………………………………………………………\n\nDoanh nghiệp chúng tôi xin cam đoan những lời khai trên là đúng và hoàn toàn chịu trách nhiệm về các nội dung kê khai trong hồ sơ đề nghị cấp thay đổi nội dung/cấp lại Giấy chứng nhận doanh nghiệp khoa học và công nghệ.",
        "metadata": {
            "chunk_index": 3,
            "total_chunks": 4,
            "prev_chunk_id": "Maudon_MAU_SO_V_5-PHU_LUC_V-268-2025-ND-CP_chunk_0002",
            "next_chunk_id": "Maudon_MAU_SO_V_5-PHU_LUC_V-268-2025-ND-CP_chunk_0004",
            "char_count": 995,
            "source_file": "Maudon/MAU SO V.5-PHU LUC V-268-2025-ND-CP.doc",
            "file_name": "MAU SO V.5-PHU LUC V-268-2025-ND-CP.doc",
            "folder": "Maudon",
            "original_extension": ".doc",
            "cleaned_at": "2026-05-21T04:47:59",
            "chunked_at": "2026-05-21T21:52:04"
        }
    },
    {
        "chunk_id": "Maudon_MAU_SO_V_5-PHU_LUC_V-268-2025-ND-CP_chunk_0004",
        "doc_id": "Maudon_MAU_SO_V_5-PHU_LUC_V-268-2025-ND-CP",
        "text": "xin cam đoan những lời khai trên là đúng và hoàn toàn chịu trách nhiệm về các nội dung kê khai trong hồ sơ đề nghị cấp thay đổi nội dung/cấp lại Giấy chứng nhận doanh nghiệp khoa học và công nghệ.\n\n|  | ..., ngày ... tháng ... năm ...<br>NGƯỜI ĐẠI DIỆN PHÁP LUẬT CỦA <br>DOANH NGHIỆP<br>(Ký, ghi rõ họ tên và đóng dấu) |\n| --- | --- |",
        "metadata": {
            "chunk_index": 4,
            "total_chunks": 4,
            "prev_chunk_id": "Maudon_MAU_SO_V_5-PHU_LUC_V-268-2025-ND-CP_chunk_0003",
            "next_chunk_id": null,
            "char_count": 334,
            "source_file": "Maudon/MAU SO V.5-PHU LUC V-268-2025-ND-CP.doc",
            "file_name": "MAU SO V.5-PHU LUC V-268-2025-ND-CP.doc",
            "folder": "Maudon",
            "original_extension": ".doc",
            "cleaned_at": "2026-05-21T04:47:59",
            "chunked_at": "2026-05-21T21:52:04"
        }
    }
]