{
    "content": "MẪU SỐ 03\n\nVăn bản yêu cầu đương sự ở Việt Nam nộp tiền tạm ứng chi phí tống đạt, thông báo văn bản tố tụng (Ban hành kèm theo Thông tư liên tịch số 01/2019/TTLT-TANDTC-BNG ngày 05/12/2019 của Tòa án nhân dân tối cao và Bộ Ngoại giao quy định về trình tự, thủ tục phối hợp giữa Tòa án nhân dân và Cơ quan đại diện nước Cộng hòa xã hội chủ nghĩa Việt Nam ở nước ngoài để thực hiện một số hoạt động tố tụng dân sự và tố tụng hành chính ở nước ngoài)\n\n| TÒA ÁN NHÂN DÂN …..(1)<br>------- | CỘNG HÒA XÃ HỘI CHỦ NGHĨA VIỆT NAM<br>Độc lập - Tự do - Hạnh phúc<br>--------------- |\n| --- | --- |\n| Số: …/TB-TA | …., ngày … tháng … năm … |\n\nTHÔNG BÁO\n\nNỘP TIỀN TẠM ỨNG CHI PHÍ TỐNG ĐẠT, THÔNG BÁO VĂN BẢN TỐ TỤNG\n\nKính gửi: Ông/Bà (2)\n\nĐịa chỉ: (3)\n\nXét thấy Ông/Bà (4) thuộc trường hợp phải nộp tiền tạm ứng chi phí tống đạt, thông báo văn bản tố tụng theo quy định của pháp luật.\n\nCăn cứ quy định tại (5), Tòa án nhân dân... (6) thông báo: Trong thời hạn 15 ngày, kể từ ngày nhận được thông báo này, Ông/Bà (7) phải nộp tiền tạm ứng lần thứ (8) chi phí tống đạt, thông báo văn bản tố tụng với số tiền là:...(bằng chữ:...) (9) vào tài khoản ngân hàng sau đây của Tòa án:\n\nSố tài khoản: (10)\n\nTên tài khoản: (11)\n\nNgân hàng/Chi nhánh ngân hàng và địa chỉ: (12)\n\nTrường hợp vì sự kiện bất khả kháng hoặc trở ngại khách quan, thì thời hạn nộp tiền tạm ứng không quá 20 ngày, kể từ ngày nhận được thông báo của Tòa án. Hết thời hạn này, nếu Ông/Bà (13) không nộp tiền tạm ứng, thì Tòa án đình chỉ giải quyết vụ, việc dân sự/vụ án hành chính theo quy định tại (14).\n\nKhi nộp tiền tạm ứng chi phí tống đạt, thông báo văn bản tố tụng Ông/Bà (15) cần lưu ý:\n\n1. Không được thanh toán phí ngân hàng vào số tiền tạm ứng phải nộp nêu trên.\n\n2. Ghi rõ nội dung nộp tiền: nộp tiền tạm ứng chi phí tống đạt, thông báo văn bản tố tụng.\n\n3. Gửi lại cho Tòa án bản chụp chứng từ nộp tiền thông qua hộp thư điện tử (16).\n\nTrường hợp cần thêm thông tin chi tiết, đề nghị Ông/Bà (17) liên hệ với Tòa án theo số điện thoại...; số Fax:...; Hộp thư điện tử:... (18)/.\n\n| Nơi nhận:<br>- Như trên;<br>- Lưu hồ sơ. | THẨM PHÁN<br><br><br><br><br>(Ký tên, ghi rõ họ tên, đóng dấu) |\n| --- | --- |\n\nHướng dẫn sử dụng Mẫu số 03\n\nMục (1): ghi tên Tòa án ban hành thông báo.\n\nMục (2): ghi Ông hoặc Bà và họ tên (đương sự là cá nhân) hoặc ghi tên (đương sự là cơ quan, tổ chức) phải nộp tiền tạm ứng chi phí tống đạt, thông báo văn bản tố tụng.\n\nMục (3): ghi địa chỉ của đương sự.\n\nMục (4): ghi như Mục (2).\n\nMục (5) ghi một trong hai điều luật (Điều 152 của Bộ luật tố tụng dân sự/Điều 353 của Luật tố tụng hành chính).\n\nMục (6): ghi như Mục (1)\n\nMục (7): ghi như Mục (2).\n\nMục (8): ghi lần yêu cầu đương sự nộp tiền tạm ứng. Ví dụ: lần thứ nhất hoặc thứ hai.\n\nMục (9): ghi cụ thể số tiền bằng đồng đô la Mỹ mà đương sự phải nộp.\n\nMục (10), (11), (12): ghi thông tin về số tài khoản thanh toán bằng ngoại tệ, tên ngân hàng, chi nhánh ngân hàng và địa chỉ.\n\nMục (13): ghi như Mục (2).\n\nMục (14): ghi điểm đ khoản 1 Điều 217 của Bộ luật tố tụng dân sự (vụ, việc dân sự) hoặc điểm d khoản 1 Điều 143 của Luật tố tụng hành chính (vụ án hành chính).\n\nMục (15), (17): ghi như Mục (2).\n\nMục (16): ghi hộp thư điện tử đầu mối của Tòa án.\n\nMục (18): ghi số điện thoại, số Fax, hộp thư điện tử đầu mối của Tòa án.\n\nNguồn: Thông tư liên tịch 01/2019/TTLT-TANDTC-BNG",
    "metadata": {
        "source_file": "thongbao/MAU SO 03-01-2019-TTLT.doc",
        "file_name": "MAU SO 03-01-2019-TTLT.doc",
        "folder": "thongbao",
        "original_extension": ".doc",
        "cleaned_at": "2026-05-20T23:39:11"
    }
}