{
    "content": "Mẫu số 17\n\nCỘNG HÒA XÃ HỘI CHỦ NGHĨA VIỆT NAM\nĐộc lập - Tự do - Hạnh phúc\n---------------\n\nTHÔNG BÁO CÔNG KHAI ĐĂNG KÝ\n\nXE MÁY CHUYÊN DÙNG\n\nHọ và tên chủ sở hữu:………………………….Số CMND (Căn cước hoặc hộ chiếu)………\n\nNgày cấp:…………………………….Nơi cấp……………………………………………..\n\nĐịa chỉ thường trú:…………………………………………………………………………..\n\nHiện tôi là chủ sở hữu xe máy chuyên dùng có đặc điểm sau:\n\nLoại xe máy chuyên dùng:……………………………………Màu sơn…………………………\n\nNhãn hiệu (mác, kiểu):………………………………………..Công suất……………………….\n\nNước sản xuất:………………………………………………...Năm sản xuất……………………\n\nSố động cơ:…………………………………………………….Số khung…………………………\n\nKích thước bao (dài x rộng x cao):…………………………..Trọng lượng……………………..\n\nNay tôi xin thông báo công khai, nếu ai có tranh chấp quyền sở hữu chiếc xe máy chuyên dùng nêu trên xin gửi về Sở Giao thông vận tải……………………………………..\n\nSau 07 ngày kể từ khi đăng tải thông báo này, nếu không có tranh chấp, Sở Giao thông vận tải sẽ tiến hành làm thủ tục đăng ký cho tôi theo quy định của pháp luật.\n\n|  | Chủ phương tiện<br>(Ký, ghi rõ họ tên) |\n| --- | --- |\n\nXác nhận của đơn vị đăng thông báo:\n\nĐã thực hiện thông báo công khai tại…………..\n\nThời hạn thông báo là 07 ngày: Từ ngày.../.../... đến ngày.../.../……\n\n|  | …………….., ngày…..tháng…..năm…...<br>Thủ trưởng đơn vị thông báo<br>(Ký tên, đóng dấu) |\n| --- | --- |\n\n* Ghi chú:\n\nBản thông báo này được lưu trong hồ sơ tại Sở Giao thông vận tải.\n\nNguồn: Thông tư 22/2019/TT/BGTVT",
    "metadata": {
        "source_file": "thongbao/MAU SO 17-PHU LUC SO 02-TT-22-2019-TT-BGTVT.doc",
        "file_name": "MAU SO 17-PHU LUC SO 02-TT-22-2019-TT-BGTVT.doc",
        "folder": "thongbao",
        "original_extension": ".doc",
        "cleaned_at": "2026-05-21T00:01:40"
    }
}