{
    "content": "PHỤ LỤC XXV\n\nTHÔNG BÁO PHƯƠNG ÁN HOẠT ĐỘNG BỒI DƯỠNG KIẾN THỨC PHÁP LUẬT VỀ GIAO THÔNG ĐƯỜNG BỘ\n(Ban hành kèm theo Thông tư số 14/2025/TT-BXD ngày 30 tháng 6 năm 2025 của Bộ trưởng Bộ Xây dựng)\n\n| CƠ QUAN CHỦ QUẢN<br>CƠ SỞ BỒI DƯỠNG<br>------- | CỘNG HÒA XÃ HỘI CHỦ NGHĨA VIỆT NAM<br>Độc lập - Tự do - Hạnh phúc <br>--------------- |\n| --- | --- |\n\nTHÔNG BÁO\nPHƯƠNG ÁN HOẠT ĐỘNG BỒI DƯỠNG KIẾN THỨC PHÁP LUẬT VỀ GIAO THÔNG ĐƯỜNG BỘ\n\nI. GIỚI THIỆU CHUNG\n\n1. Tên cơ sở bồi dưỡng (Trường hoặc Trung tâm):\n\nGiám đốc:…………\n\nĐịa chỉ liên lạc:...\n\nĐiện thoại:...Fax:...\n\n2. Cơ quan quản lý cấp trên trực tiếp:...\n\n3. Quyết định thành lập số... ngày ... / ... / ... của...\n\nII. THÔNG TIN BỒI DƯỠNG KIẾN THỨC PHÁP LUẬT VỀ GIAO THÔNG ĐƯỜNG BỘ\n\n1. Bồi dưỡng từ năm... theo văn bản số...ngày ... / ... / ... của...\n\nTừ khi thành lập đến nay đã mở được...lớp, bồi dưỡng được... học viên\n\nTừ khi thành lập đến nay đã cấp...chứng chỉ, cấp lại...chứng chỉ\n\n2. Hiện nay đang bồi dưỡng... học viên, thời gian bồi dưỡng...tháng.\n\n(Trường hợp chưa bồi dưỡng không nêu các điểm 1, 2 phần II)\n\n3. Tổng số phòng học lý thuyết hiện có:\n\nĐánh giá cụ thể từng phòng học lý thuyết và các thiết bị dạy học: sa hình và hệ thống biển báo hiệu giao thông đường bộ; chất lượng từng phòng học.\n\n4. Mục tiêu, kế hoạch giảng dạy: tài liệu giảng dạy, nội dung kiểm tra.\n\n5. Đội ngũ giáo viên\n\n- Số lượng giáo viên:...\n\n(Có danh sách kèm theo)\n\n6. Đánh giá chung:\n\n……………………………………………………………………………\n\n……………………………………………………………………………\n\n7. Đăng ký thời gian bồi dưỡng: từ ngày…..\n\n|  | NGƯỜI ĐỨNG ĐẦU <br>CƠ SỞ BỒI DƯỠNG<br>(Ký tên, đóng dấu) |\n| --- | --- |\n\nDANH SÁCH TRÍCH NGANG GIÁO VIÊN\n\n| Số TT | Họ và tên | Ngày tháng năm sinh | Số CCCD/CC | Đơn vị công tác | Hình thức tuyển dụng | Hình thức tuyển dụng | Trình độ | Trình độ | Trình độ | Thâm niên dạy học | Ghi chú |\n| --- | --- | --- | --- | --- | --- | --- | --- | --- | --- | --- | --- |\n| Số TT | Họ và tên | Ngày tháng năm sinh | Số CCCD/CC | Đơn vị công tác | Biên chế | Hợp đồng (thời hạn) | Văn hóa | Chuyên môn | Sư phạm | Thâm niên dạy học | Ghi chú |\n| (1) | (2) | (3) | (4) | (5) | (6) | (7) | (8) | (9) | (10) | (13) | (14) |\n| 1 |  |  |  |  |  |  |  |  |  |  |  |\n| 2 |  |  |  |  |  |  |  |  |  |  |  |\n| 3 |  |  |  |  |  |  |  |  |  |  |  |\n| … |  |  |  |  |  |  |  |  |  |  |  |",
    "metadata": {
        "source_file": "thongbao/PHU LUC XXV-14-2025-TT-BXD.doc",
        "file_name": "PHU LUC XXV-14-2025-TT-BXD.doc",
        "folder": "thongbao",
        "original_extension": ".doc",
        "cleaned_at": "2026-05-21T00:37:08"
    }
}