[
    {
        "chunk_id": "mauphieu_MAU_SO_01-1345-QD-CT_chunk_0001",
        "doc_id": "mauphieu_MAU_SO_01-1345-QD-CT",
        "text": "| BỘ TÀI CHÍNH <br>CỤC THUẾ | Mẫu số 01 |\n| --- | --- |\n\nPHIẾU KHẢO SÁT\n\nSự hài lòng của người nộp thuế đối với sự phục vụ của cơ quan thuế\n(Kèm theo Quyết định số 1345/QĐ-CT ngày 20/6/2025 của Cục Thuế)\n___\n\nMã số thuế của người nộp thuế thực hiện đánh giá <Hệ thống tự sinh>\n\nKhảo sát sự hài lòng của người nộp thuế đối với cơ quan thuế <Hệ thống tự sinh>\n\nCục Thuế là đơn vị thuộc Bộ Tài chính thực hiện việc khảo sát sự hài lòng của người nộp thuế đối với sự phục vụ của cơ quan thuế nhằm thu nhận những thông tin cần thiết với mục tiêu xây dựng ngành Thuế Việt Nam hiện đại, tinh gọn, hoạt động hiệu lực, hiệu quả; công tác quản lý thuế thống nhất, minh bạch, chuyên sâu, chuyên nghiệp; đẩy mạnh ứng dụng công nghệ thông tin, đơn giản hóa thủ tục hành chính, giảm chi phí tuân thủ của người nộp thuế; nâng cao nhận thức, văn hoá thực thi công vụ lấy người nộp thuế làm trung tâm trong đội ngũ công chức thuế.",
        "metadata": {
            "chunk_index": 1,
            "total_chunks": 5,
            "prev_chunk_id": null,
            "next_chunk_id": "mauphieu_MAU_SO_01-1345-QD-CT_chunk_0002",
            "char_count": 913,
            "source_file": "mauphieu/MAU SO 01-1345-QD-CT.doc",
            "file_name": "MAU SO 01-1345-QD-CT.doc",
            "folder": "mauphieu",
            "original_extension": ".doc",
            "cleaned_at": "2026-05-21T01:30:40",
            "chunked_at": "2026-05-21T21:52:06"
        }
    },
    {
        "chunk_id": "mauphieu_MAU_SO_01-1345-QD-CT_chunk_0002",
        "doc_id": "mauphieu_MAU_SO_01-1345-QD-CT",
        "text": "nghệ thông tin, đơn giản hóa thủ tục hành chính, giảm chi phí tuân thủ của người nộp thuế; nâng cao nhận thức, văn hoá thực thi công vụ lấy người nộp thuế làm trung tâm trong đội ngũ công chức thuế.\n\nTất cả thông tin trong Phiếu khảo sát này chỉ sử dụng vào mục đích thống kê, nghiên cứu tiến hành cải cách trong thời gian tới. Cục Thuế cam kết bảo mật thông tin và danh tính người nộp thuế tham gia khảo sát.\n\nVới mong muốn nhận được những thông tin sát thực nhất, Cục Thuế trân trọng đề nghị người tham gia trả lời Phiếu khảo sát là Lãnh đạo hoặc người trực tiếp xử lý công việc liên quan tới lĩnh vực thuế của người nộp thuế để cung cấp một cách đầy đủ, chính xác, khách quan về nhưng thông tin trong Phiếu khảo sát.\n\nNgười nộp thuế tham gia khảo sát có thể lựa chọn đánh giá một số hoặc toàn bộ các tiêu chí trong Phiếu khảo sát này theo các nội dung sau đây:",
        "metadata": {
            "chunk_index": 2,
            "total_chunks": 5,
            "prev_chunk_id": "mauphieu_MAU_SO_01-1345-QD-CT_chunk_0001",
            "next_chunk_id": "mauphieu_MAU_SO_01-1345-QD-CT_chunk_0003",
            "char_count": 863,
            "source_file": "mauphieu/MAU SO 01-1345-QD-CT.doc",
            "file_name": "MAU SO 01-1345-QD-CT.doc",
            "folder": "mauphieu",
            "original_extension": ".doc",
            "cleaned_at": "2026-05-21T01:30:40",
            "chunked_at": "2026-05-21T21:52:06"
        }
    },
    {
        "chunk_id": "mauphieu_MAU_SO_01-1345-QD-CT_chunk_0003",
        "doc_id": "mauphieu_MAU_SO_01-1345-QD-CT",
        "text": "khách quan về nhưng thông tin trong Phiếu khảo sát.\n\nNgười nộp thuế tham gia khảo sát có thể lựa chọn đánh giá một số hoặc toàn bộ các tiêu chí trong Phiếu khảo sát này theo các nội dung sau đây:\n\n| Tiêu chí |  | Mức độ hài lòng | Mức độ hài lòng | Mức độ hài lòng | Mức độ hài lòng | Mức độ hài lòng | Mức độ hài lòng |  |\n| --- | --- | --- | --- | --- | --- | --- | --- | --- |\n| Tiêu chí | Rất không hài lòng | Không hài lòng | Không hài lòng | Bình thường | Bình thường | Hài lòng | Hài lòng | Rất hài lòng |\n| A. CÔNG TÁC XÂY DỰNG, TỔ CHỨC THỰC HIỆN CHÍNH SÁCH THUẾ, QUẢN LÝ THUẾ |  |  |  |  |  |  |  |  |\n| 1. Trách nhiệm giải trình của cơ quan thuế |  |  |  |  |  |  |  |  |\n| 1. Cơ quan thuế cung cấp, phổ biến, hướng dẫn, giải thích thực hiện chính sách thuế, thủ tục hành chính thuế theo nhiều hình thức, dễ tìm, dễ thấy, kịp thời và dễ hiểu |  |  |  |  |  |  |  |  |\n| II. Sự tham gia của người nộp thuế và kết quả tác động trong việc xây dựng, tổ chức thực hiện chính sách thuế, quản lý thuế |  |  |  |  |  |  |  |  |\n| 2. Cơ quan thuế tổ chức nhiều hình thức để người nộp thuế dễ dàng tham gia góp ý kiến xây dựng chính sách thuế và và công tác quản lý thuế tại địa phương |  |  |  |  |  |  |  |  |\n| 3. Các quy định về cơ chế quản lý thuế phù hợp với thực tiễn và có hiệu quả nâng cao tính tuân thủ pháp luật của người nộp thuế |  |  |  |  |  |  |  |  |\n| 4. Cơ quan thuế, đội ngũ công chức thuế ở địa phương có năng lực và thực thi công vụ tốt hơn trong thời gian vừa qua |  |  |  |  |  |  |  |  |\n| B. VIỆC CUNG ỨNG DỊCH VỤ CÔNG CỦA CƠ QUAN THUẾ |  |  |  |  |  |  |  |  |\n| I. Tiếp cận dịch vụ |  |  |  |  |  |  |  |  |\n| 5. Bộ phận một cửa, nơi đón tiếp người nộp thuế của cơ quan thuế có biển hiệu, hướng dẫn rõ ràng, dễ tìm, dễ thấy |  |  |  |  |  |  |  |  |\n| 6. Bộ phận một cửa, nơi tiếp đón người nộp thuế của cơ quan thuế có cơ sở vật chất, trang thiết bị phục vụ đầy đủ, chất lượng tốt, giúp giải quyết công việc dễ dàng hơn |  |  |  |  |  |  |  |  |\n| 7. Tra cứu chính sách thuế, thủ tục hành chính về thuế qua website, mạng xã hội của cơ quan thuế dễ dàng, thuận tiện |  |  |  |  |  |  |  |  |\n| 8. Cơ quan thuế hướng dẫn người nộp thuế sử dụng các ứng dụng của ngành thuế để thực hiện thủ tục hành chính thuế, tra cứu thông tin về thuế kịp thời, dễ hiểu, dễ thực hiện |  |  |  |  |  |  |  |  |\n| II. Thực hiện thủ tục hành chính thuế |  |  |  |  |  |  |  |  |\n| 9. Trình tự, cách thức thực hiện, hồ sơ, yêu cầu, điều kiện thực hiện thủ tục hành chính thuế đơn giản, dễ hiểu, dễ thực hiện |  |  |  |  |  |  |  |  |\n| 10. Việc nộp hồ sơ thủ tục hành chính thuế tại bộ phận một cửa của cơ quan thuế dễ dàng, thuận tiện |  |  |  |  |  |  |  |  |\n| 11. Việc nộp hồ sơ thủ tục hành chính theo phương thức điện tử dễ dàng, thuận tiện |  |  |  |  |  |  |  |  |\n| 12. Yêu cầu giải trình, bổ sung hồ sơ thuế của cơ quan thuế trong quá trình thực hiện thủ tục hành chính là đúng quy định và phù hợp |  |  |  |  |  |  |  |  |\n| 13. Thực hiện thủ tục đăng ký thuế, thay đổi thông tin đăng ký thuế, chuyển địa điểm hoạt động kinh doanh, đóng mã số thuế dễ dàng, thuận tiện |  |  |  |  |  |  |  |  |\n| 14. Thực hiện thủ tục khai thuế dễ dàng, thuận tiện |  |  |  |  |  |  |  |  |\n| 15. Thực hiện thủ tục hoàn thuế, miễn thuế, giảm thuế dễ dàng, thuận tiện |  |  |  |  |  |  |  |  |\n| 16. Thực hiện thủ tục nộp thuế, xác định nghĩa vụ nộp thuế dễ dàng, thuận tiện |  |  |  |  |  |  |  |  |\n| 17. Yêu cầu người nộp thuế đóng phí/lệ phí giải quyết thủ tục hành chính đúng theo quy định |  |  |  |  |  |  |  |  |\n| 18. Hệ thống đường truyền dữ liệu hoạt động tốt và ổn định khi thực hiện thủ tục hành chính thuế bằng phương thức điện tử |  |  |  |  |  |  |  |  |\n| III. Công chức giải quyết công việc |  |  |  |  |  |  |  |  |\n| 19. Công chức ở bộ phận một cửa có thái độ, tác phong, giao tiếp lịch sự, tôn trọng người nộp thuế |  |  |  |  |  |  |  |  |\n| 20. Công chức ở bộ phận một cửa hướng dẫn hồ sơ dễ hiểu, đầy đủ, giúp người nộp thuế dễ dàng hoàn thiện hồ sơ |  |  |  |  |  |  |  |  |\n| 21. Công chức ở bộ phận một cửa tuân thủ đúng quy định trong giải quyết thủ tục hành chính cho người nộp thuế |  |  |  |  |  |  |  |  |\n| 22. Công chức trực tiếp làm việc/giải quyết thủ tục hành chính có thái độ, tác phong, giao tiếp lịch sự, tôn trọng người nộp thuế |  |  |  |  |  |  |  |  |\n| 23. Công chức trực tiếp làm việc/giải quyết thủ tục hành chính có năng lực, chuyên môn |  |  |  |  |  |  |  |  |\n| IV. Kết quả thực hiện thủ tục hành chính thuế |  |  |  |  |  |  |  |  |\n| 24. Thời gian giải quyết thủ tục hành chính đúng quy định |  |  |  |  |  |  |  |  |\n| 25. Trả kết quả giải quyết thủ tục hành chính đúng hẹn |  |  |  |  |  |  |  |  |\n| 26. Kết quả giải quyết thủ tục hành chính cho người nộp thuế đúng quy định |  |  |  |  |  |  |  |  |\n| 27. Kết quả giải quyết thủ tục hành chính cho người nộp thuế đảm bảo tính công bằng |  |  |  |  |  |  |  |  |\n| V. Công tác kiểm tra thuế của cơ quan thuế tại trụ sở người nộp thuế |  |  |  |  |  |  |  |  |\n| 28. Tần suất các cuộc kiểm tra tại trụ sở người nộp thuế là phù hợp |  |  |  |  |  |  |  |  |\n| 29. Thời gian kiểm tra thuế tại trụ sở người nộp thuế đúng với thời gian trong quyết định kiểm tra đã ban hành |  |  |  |  |  |  |  |  |\n| 30. Nội dung kiểm tra thuế không bị chồng chéo, trùng lặp |  |  |  |  |  |  |  |  |\n| 31. Hoạt động kiểm tra thuế không cản trở hoạt động bình thường của người nộp thuế |  |  |  |  |  |  |  |  |\n| 32. Thái độ, tác phong của công chức thuế thực hiện kiểm tra thuế |  |  |  |  |  |  |  |  |\n| 33. Năng lực chuyên môn của công chức thuế thực hiện kiểm tra thuế |  |  |  |  |  |  |  |  |\n| 34. Nội dung biên bản, kết luận kiểm tra của cơ quan thuế |  |  |  |  |  |  |  |  |\n| VI. Công tác tiếp nhận, giải quyết khiếu nại, tố cáo và xử lý phản ánh kiến nghị của cơ quan thuế |  |  |  |  |  |  |  |  |\n| 35. Việc gửi thông tin khiếu nại, tố cáo, phản ánh, kiến nghị đến cơ quan thuế dễ dàng, thuận tiện |  |  |  |  |  |  |  |  |\n| 36. Việc giải quyết khiếu nại, tố cáo, xử lý phản ánh kiến nghị kịp thời, đúng thời gian quy định |  |  |  |  |  |  |  |  |\n| 37. Kết quả giải quyết khiếu nại, tố cáo, xử lý phản ánh kiến nghị công tâm, khách quan, đúng quy định |  |  |  |  |  |  |  |  |\n| 38. Thái độ, tác phong của công chức thuế khi làm việc với người nộp thuế về nội dung khiếu nại, tố cáo, phản ánh, kiến nghị |  |  |  |  |  |  |  |  |\n| 39. Năng lực chuyên môn của công chức thuế khí làm việc với người nộp thuế về nội dung khiếu nại, tố cáo, phản ánh, kiến nghị |  |  |  |  |  |  |  |  |\n| C. NHU CẦU, MONG ĐỢI CỦA NGƯỜI NỘP THUẾ ĐỐI VỚI SỰ PHỤC VỤ CỦA CƠ QUAN THUẾ | C. NHU CẦU, MONG ĐỢI CỦA NGƯỜI NỘP THUẾ ĐỐI VỚI SỰ PHỤC VỤ CỦA CƠ QUAN THUẾ | C. NHU CẦU, MONG ĐỢI CỦA NGƯỜI NỘP THUẾ ĐỐI VỚI SỰ PHỤC VỤ CỦA CƠ QUAN THUẾ | C. NHU CẦU, MONG ĐỢI CỦA NGƯỜI NỘP THUẾ ĐỐI VỚI SỰ PHỤC VỤ CỦA CƠ QUAN THUẾ | C. NHU CẦU, MONG ĐỢI CỦA NGƯỜI NỘP THUẾ ĐỐI VỚI SỰ PHỤC VỤ CỦA CƠ QUAN THUẾ | C. NHU CẦU, MONG ĐỢI CỦA NGƯỜI NỘP THUẾ ĐỐI VỚI SỰ PHỤC VỤ CỦA CƠ QUAN THUẾ | C. NHU CẦU, MONG ĐỢI CỦA NGƯỜI NỘP THUẾ ĐỐI VỚI SỰ PHỤC VỤ CỦA CƠ QUAN THUẾ | C. NHU CẦU, MONG ĐỢI CỦA NGƯỜI NỘP THUẾ ĐỐI VỚI SỰ PHỤC VỤ CỦA CƠ QUAN THUẾ | C. NHU CẦU, MONG ĐỢI CỦA NGƯỜI NỘP THUẾ ĐỐI VỚI SỰ PHỤC VỤ CỦA CƠ QUAN THUẾ |\n| Tiêu chí | Nhu cầu, mong đợi của người nộp thuế | Nhu cầu, mong đợi của người nộp thuế | Nhu cầu, mong đợi của người nộp thuế | Nhu cầu, mong đợi của người nộp thuế | Nhu cầu, mong đợi của người nộp thuế | Nhu cầu, mong đợi của người nộp thuế | Nhu cầu, mong đợi của người nộp thuế | Nhu cầu, mong đợi của người nộp thuế |\n| Tiêu chí | Không mong muốn | Không mong muốn | Khá mong muốn | Khá mong muốn | Mong muốn | Mong muốn | Rất mong muốn | Rất mong muốn |\n| 40. Nâng cao tính công khai, minh bạch trong cung cấp thông tin cho người nộp thuế |  |  |  |  |  |  |  |  |\n| 41. Nâng cao chất lượng của công chức trong giải quyết công việc cho người nộp thuế |  |  |  |  |  |  |  |  |\n| 42. Nâng cao tinh thần, thái độ phục vụ của công chức thuế đối với người nộp thuế trong giải quyết công việc cho người nộp thuế |  |  |  |  |  |  |  |  |\n| 43. Tăng cường ứng dụng công nghệ thông tin, chuyển đổi số trong giải quyết công việc cho người nộp thuế |  |  |  |  |  |  |  |  |\n| 44. Nâng cao chất lượng dịch vụ công trực tuyến để tạo điều kiện thuận lợi, dễ dàng cho người dân trong thực hiện dịch vụ công trực tuyến |  |  |  |  |  |  |  |  |",
        "metadata": {
            "chunk_index": 3,
            "total_chunks": 5,
            "prev_chunk_id": "mauphieu_MAU_SO_01-1345-QD-CT_chunk_0002",
            "next_chunk_id": "mauphieu_MAU_SO_01-1345-QD-CT_chunk_0004",
            "char_count": 8333,
            "source_file": "mauphieu/MAU SO 01-1345-QD-CT.doc",
            "file_name": "MAU SO 01-1345-QD-CT.doc",
            "folder": "mauphieu",
            "original_extension": ".doc",
            "cleaned_at": "2026-05-21T01:30:40",
            "chunked_at": "2026-05-21T21:52:06"
        }
    },
    {
        "chunk_id": "mauphieu_MAU_SO_01-1345-QD-CT_chunk_0004",
        "doc_id": "mauphieu_MAU_SO_01-1345-QD-CT",
        "text": "thuế |  |  |  |  |  |  |  |  |\n| 44. Nâng cao chất lượng dịch vụ công trực tuyến để tạo điều kiện thuận lợi, dễ dàng cho người dân trong thực hiện dịch vụ công trực tuyến |  |  |  |  |  |  |  |  |\n\nNgoài các nội dung trên, người nộp thuế có thể cho thêm các ý kiến khác nhằm nâng cao chất lượng phục vụ người nộp thuế trong thời gian tới:\n\n45. Người nộp thuế có phải trả các khoản chi phí không chính thức/ngoài quy định cho cơ quan thuế/công chức thuế khi giải quyết công việc hoặc thực hiện thủ tục hành chính với cơ quan thuế không?\n\n| - Khi thực hiện thủ tục hành chính | Có | Không |\n| --- | --- | --- |\n| - Khi được kiểm tra | Có | Không |\n| - Khi giải quyết khiếu nại | Có | Không |\n| - Trong các công việc khác | Có | Không |\n\n46. Ý kiến góp ý khác (NNT cho ý kiến cụ thể về những nội dung đánh giá “Rất không hài lòng” hoặc phản ánh về tình trạng gây khó khăn, gây phiền hà, nhũng nhiễu của công chức thuế...)\n\n………………………………………………………………………………………………\n\n………………………………………………………………………………………………",
        "metadata": {
            "chunk_index": 4,
            "total_chunks": 5,
            "prev_chunk_id": "mauphieu_MAU_SO_01-1345-QD-CT_chunk_0003",
            "next_chunk_id": "mauphieu_MAU_SO_01-1345-QD-CT_chunk_0005",
            "char_count": 994,
            "source_file": "mauphieu/MAU SO 01-1345-QD-CT.doc",
            "file_name": "MAU SO 01-1345-QD-CT.doc",
            "folder": "mauphieu",
            "original_extension": ".doc",
            "cleaned_at": "2026-05-21T01:30:40",
            "chunked_at": "2026-05-21T21:52:06"
        }
    },
    {
        "chunk_id": "mauphieu_MAU_SO_01-1345-QD-CT_chunk_0005",
        "doc_id": "mauphieu_MAU_SO_01-1345-QD-CT",
        "text": "đánh giá “Rất không hài lòng” hoặc phản ánh về tình trạng gây khó khăn, gây phiền hà, nhũng nhiễu của công chức thuế...)\n\n………………………………………………………………………………………………\n\n………………………………………………………………………………………………\n\nXIN TRÂN TRỌNG CẢM ƠN",
        "metadata": {
            "chunk_index": 5,
            "total_chunks": 5,
            "prev_chunk_id": "mauphieu_MAU_SO_01-1345-QD-CT_chunk_0004",
            "next_chunk_id": null,
            "char_count": 219,
            "source_file": "mauphieu/MAU SO 01-1345-QD-CT.doc",
            "file_name": "MAU SO 01-1345-QD-CT.doc",
            "folder": "mauphieu",
            "original_extension": ".doc",
            "cleaned_at": "2026-05-21T01:30:40",
            "chunked_at": "2026-05-21T21:52:06"
        }
    }
]