[
    {
        "chunk_id": "mauphieu_MAU_SO_03-PHU_LUC_01-05-2025-TT-BVHTTDL_chunk_0001",
        "doc_id": "mauphieu_MAU_SO_03-PHU_LUC_01-05-2025-TT-BVHTTDL",
        "text": "Mẫu số 03. Phiếu thẩm định hiện vật dự kiến mua của Hội đồng thẩm định\n\n| HỘI ĐỒNG THẨM ĐỊNH<br>MUA HIỆN VẬT<br>Cho…(tên bảo tàng mua hiện vật)….<br>------- | CỘNG HÒA XÃ HỘI CHỦ NGHĨA VIỆT NAM<br>Độc lập - Tự do - Hạnh phúc<br>--------------- |\n| --- | --- |\n|  | ………., ngày ….. tháng …. năm ….. |\n\nPHIẾU THẨM ĐỊNH HIỆN VẬT DỰ KIẾN MUA\n\nHọ và tên người ghi phiếu:………………..…………………………………….\n\nChức danh trong Hội đồng thẩm định: …………………………………………\n\nĐịa chỉ: ………………………………………… Điện thoại:………………….",
        "metadata": {
            "chunk_index": 1,
            "total_chunks": 3,
            "prev_chunk_id": null,
            "next_chunk_id": "mauphieu_MAU_SO_03-PHU_LUC_01-05-2025-TT-BVHTTDL_chunk_0002",
            "char_count": 488,
            "source_file": "mauphieu/MAU SO 03-PHU LUC 01-05-2025-TT-BVHTTDL.doc",
            "file_name": "MAU SO 03-PHU LUC 01-05-2025-TT-BVHTTDL.doc",
            "folder": "mauphieu",
            "original_extension": ".doc",
            "cleaned_at": "2026-05-21T01:51:00",
            "chunked_at": "2026-05-21T21:52:07"
        }
    },
    {
        "chunk_id": "mauphieu_MAU_SO_03-PHU_LUC_01-05-2025-TT-BVHTTDL_chunk_0002",
        "doc_id": "mauphieu_MAU_SO_03-PHU_LUC_01-05-2025-TT-BVHTTDL",
        "text": "năm ….. |\n\nPHIẾU THẨM ĐỊNH HIỆN VẬT DỰ KIẾN MUA\n\nHọ và tên người ghi phiếu:………………..…………………………………….\n\nChức danh trong Hội đồng thẩm định: …………………………………………\n\nĐịa chỉ: ………………………………………… Điện thoại:………………….\n\n| TT | Tên hiện vật | Số TT trong Danh sách hiện vật dự kiến sưu tầm | Giá chào bán do chủ sở hữu đề xuất (VNĐ) | Giá mua do tổ chức, cá nhân đi sưu tầm thương thảo với chủ sở hữu (VNĐ)* | Giá mua do tổ chức, cá nhân đi sưu tầm thương thảo với chủ sở hữu (VNĐ)* | Giá mua do tổ chức, cá nhân đi sưu tầm thương thảo với chủ sở hữu (VNĐ)* | Giá mua do Hội đồng khoa học bảo tàng đề xuất (VNĐ) | Ý kiến của thành viên Hội đồng thẩm định | Ý kiến của thành viên Hội đồng thẩm định | Ý kiến của thành viên Hội đồng thẩm định | Ghi chú |\n| --- | --- | --- | --- | --- | --- | --- | --- | --- | --- | --- | --- |\n| TT | Tên hiện vật | Số TT trong Danh sách hiện vật dự kiến sưu tầm | Giá chào bán do chủ sở hữu đề xuất (VNĐ) | Lần 1 | Lần 2 | Lần 3 | Giá mua do Hội đồng khoa học bảo tàng đề xuất (VNĐ) | Đồng ý mua | Không đồng ý mua | Giá mua (VNĐ) |  |\n| 1 | 2 | 3 | 4 | 5 | 6 | 7 | 8 | 9 | 10 | 11 | 12 |\n| 1 |  |  |  |  |  |  |  |  |  |  |  |",
        "metadata": {
            "chunk_index": 2,
            "total_chunks": 3,
            "prev_chunk_id": "mauphieu_MAU_SO_03-PHU_LUC_01-05-2025-TT-BVHTTDL_chunk_0001",
            "next_chunk_id": "mauphieu_MAU_SO_03-PHU_LUC_01-05-2025-TT-BVHTTDL_chunk_0003",
            "char_count": 1141,
            "source_file": "mauphieu/MAU SO 03-PHU LUC 01-05-2025-TT-BVHTTDL.doc",
            "file_name": "MAU SO 03-PHU LUC 01-05-2025-TT-BVHTTDL.doc",
            "folder": "mauphieu",
            "original_extension": ".doc",
            "cleaned_at": "2026-05-21T01:51:00",
            "chunked_at": "2026-05-21T21:52:07"
        }
    },
    {
        "chunk_id": "mauphieu_MAU_SO_03-PHU_LUC_01-05-2025-TT-BVHTTDL_chunk_0003",
        "doc_id": "mauphieu_MAU_SO_03-PHU_LUC_01-05-2025-TT-BVHTTDL",
        "text": "| Giá mua do Hội đồng khoa học bảo tàng đề xuất (VNĐ) | Đồng ý mua | Không đồng ý mua | Giá mua (VNĐ) |  |\n| 1 | 2 | 3 | 4 | 5 | 6 | 7 | 8 | 9 | 10 | 11 | 12 |\n| 1 |  |  |  |  |  |  |  |  |  |  |  |\n\nTổng số hiện vật đề xuất mua: ... (bằng chữ)\n\nTổng số tiền mua hiện vật: ... (bằng chữ)\n\nÝ kiến bổ sung của thành viên Hội đồng thẩm định:\n\n...\n\n| NGƯỜI GHI PHIẾU<br>(Ký, ghi rõ họ tên) | CHỦ TỊCH HỘI ĐỒNG THẨM ĐỊNH<br>(Ký, ghi rõ họ tên) |\n| --- | --- |\n\n* Trường hợp chỉ thương thảo 1 lần hoặc 2 lần thì chỉ ghi thông tin vào cột tương ứng.",
        "metadata": {
            "chunk_index": 3,
            "total_chunks": 3,
            "prev_chunk_id": "mauphieu_MAU_SO_03-PHU_LUC_01-05-2025-TT-BVHTTDL_chunk_0002",
            "next_chunk_id": null,
            "char_count": 542,
            "source_file": "mauphieu/MAU SO 03-PHU LUC 01-05-2025-TT-BVHTTDL.doc",
            "file_name": "MAU SO 03-PHU LUC 01-05-2025-TT-BVHTTDL.doc",
            "folder": "mauphieu",
            "original_extension": ".doc",
            "cleaned_at": "2026-05-21T01:51:00",
            "chunked_at": "2026-05-21T21:52:07"
        }
    }
]