{
    "content": "| Biểu TS-08<br>Ban hành kèm theo TT số …/2022/TT-BTTTT<br>Ngày nhận báo cáo: Trước ngày 15 tháng tiếp theo | SỐ VỤ CAN NHIỄU TẦN SỐ VÔ TUYẾN ĐIỆN CÓ HẠI | Đơn vị báo cáo: Cục TS<br>Đơn vị nhận báo cáo: Vụ KHTC, VP Bộ |\n| --- | --- | --- |\n| Biểu TS-08<br>Ban hành kèm theo TT số …/2022/TT-BTTTT<br>Ngày nhận báo cáo: Trước ngày 15 tháng tiếp theo | Tháng… /20… | Đơn vị báo cáo: Cục TS<br>Đơn vị nhận báo cáo: Vụ KHTC, VP Bộ |\n\nĐơn vị tính: Vụ\n\n| TT | Tỉnh/thành phố | Mã đơn vị | Nghiệp vụ bị can nhiễu | Nghiệp vụ bị can nhiễu | Nghiệp vụ bị can nhiễu | Nghiệp vụ bị can nhiễu | Nghiệp vụ bị can nhiễu | Nghiệp vụ bị can nhiễu | Nghiệp vụ bị can nhiễu | Tổng số (8=1+2+ 3+ 4+ 5+ 6+ 7) | Trong đó, số vụ chưa kết thúc |\n| --- | --- | --- | --- | --- | --- | --- | --- | --- | --- | --- | --- |\n| TT | Tỉnh/thành phố | Mã đơn vị | Hàng không | Di động công cộng | Di động dùng riêng | Phát thanh, truyền hình | Quốc phòng, an ninh | An toàn cứu nạn, phòng chống lụt, bão | Khác |  |  |\n| A | B | C | 1 | 2 | 3 | 4 | 5 | 6 | 7 | 8 | 9 |\n|  | CẢ NƯỚC |  |  |  |  |  |  |  |  |  |  |\n| 1 | Hà Nội | 01 |  |  |  |  |  |  |  |  |  |\n| 2 | Hà Giang | 02 |  |  |  |  |  |  |  |  |  |\n| … | … | … |  |  |  |  |  |  |  |  |  |\n| 63 | Cà Mau | 96 |  |  |  |  |  |  |  |  |  |\n\n| TỔNG HỢP, LẬP BIỂU<br>(Thông tin người thực hiện) | KIỂM TRA BIỂU<br>(Thông tin người thực hiện) | Hà Nội, ngày … tháng … năm 20…<br>CỤC TRƯỞNG<br>(Ký điện tử) |\n| --- | --- | --- |\n\na) Khái niệm, phương pháp tính\n\nSố vụ can nhiễu có hại: Là số vụ can nhiễu có hại phát sinh trong kỳ báo cáo. (Can nhiễu (nhiễu có hại) là ảnh hưởng có hại của năng lượng điện từ do việc phát xạ bức xạ hoặc cảm ứng gây mất an toàn hoặc cản trở, làm gián đoạn hoạt động của thiết bị, hệ thống thiết bị vô tuyến đang khai thác hợp pháp).\n\nb) Cách ghi biểu\n\n| Cột | Nội dung |\n| --- | --- |\n| (B, C) | Ghi thông tin như cách ghi áp dụng đối với các Cột B, C tương ứng tại biểu mẫu TS-03. |\n| (1) | Số vụ can nhiễu có hại mạng đài điều hành, dẫn đường hàng không trong kỳ báo cáo tại địa bàn có tên tại Cột B. |\n|  | Các cột sau đây ghi thông tin tương tự như cách ghi đã áp dụng cho Cột 1: |\n| (2) | Số vụ can nhiễu có hại mạng di động công cộng. |\n| (3) | Số vụ can nhiễu có hại mạng di động dùng riêng. |\n| (4) | Số vụ can nhiễu có hại mạng đài phát thanh truyền hình. |\n| (5) | Số vụ can nhiễu có hại mạng đài quốc phòng, an ninh. |\n| (6) | Số vụ can nhiễu có hại mạng an toàn cứu nạn, phòng chống lụt, bão. |\n| (7) | Số vụ can nhiễu có hại mạng đài khác trong kỳ báo cáo. |\n|  | Số liệu cả nước được tổng hợp tương ứng từ số liệu các tỉnh/thành phố trên biểu. |\n\nc) Nguồn số liệu\n\nBiểu được lập từ dữ liệu do các Trạm kiểm soát tần số cung cấp và từ dữ liệu hành chính của Cục TS.",
    "metadata": {
        "source_file": "maubaocao/BIEU TS-08-TT-04-2022-TT-BTTTT.doc",
        "file_name": "BIEU TS-08-TT-04-2022-TT-BTTTT.doc",
        "folder": "maubaocao",
        "original_extension": ".doc",
        "cleaned_at": "2026-05-21T03:07:37"
    }
}