{
    "content": "| CTCK:...<br>Địa chỉ:... | Mẫu số B02a - CTCK<br>(Ban hành theo TT số 334/2016/TT-BTC ngày 27/12/2016 của Bộ Tài chính) |\n| --- | --- |\n\nBÁO CÁO KẾT QUẢ HOẠT ĐỘNG GIỮA NIÊN ĐỘ\n\nNăm….\n\nĐơn vị: Đồng Việt Nam\n\n| CHỈ TIÊU | Mã số | Thuyết minh | Quý | Quý | Lũy kế từ đầu năm đến cuối quý này | Lũy kế từ đầu năm đến cuối quý này |\n| --- | --- | --- | --- | --- | --- | --- |\n| CHỈ TIÊU | Mã số | Thuyết minh | Năm nay | Năm trước | Năm nay | Năm trước |\n| 1 | 2 | 3 | 4 | 5 | 6 | 7 |\n| A. Lãi, lỗ |  |  |  |  |  |  |\n| I. DOANH THU HOẠT ĐỘNG |  |  |  |  |  |  |\n| ... (*) |  |  |  |  |  |  |\n\n| Người lập biểu<br>(Ký, họ tên) | Kế toán trưởng<br>(Ký, họ tên) | ..., ngày... tháng... năm... <br>Người đại diện theo pháp luật<br>(Ký, họ tên, đóng dấu) |\n| --- | --- | --- |\n\n(*) Nội dung các chỉ tiêu và mã số trên báo cáo này tương tự như các chỉ tiêu của Báo cáo kết quả hoạt động năm - Mẫu B02-CTCK\n\nNguồn: Thông tư 334/2016/TT-BTC",
    "metadata": {
        "source_file": "maubaocao/MAU SO B02a-CTCK-334-2016-TT-BTC.doc",
        "file_name": "MAU SO B02a-CTCK-334-2016-TT-BTC.doc",
        "folder": "maubaocao",
        "original_extension": ".doc",
        "cleaned_at": "2026-05-21T03:38:47"
    }
}