{
    "content": "PHỤ LỤC II\n\nMẪU ĐƠN ĐỀ NGHỊ CẤP LẠI GIẤY CHỨNG NHẬN LƯU HÀNH TỰ DO\n(Ban hành kèm theo Thông tư số 21/2020/TT-BTTTT ngày 07 tháng 9 năm 2020 của Bộ trưởng Bộ Thông tin và Truyền thông)\n\nBỘ THÔNG TIN VÀ TRUYỀN THÔNG\nMINISTRY OF INFORMATION AND COMMUNICATIONS\n\nĐịa chỉ: 18 Nguyễn Du, quận Hai Bà Trưng, Hà Nội\nAddress: 18 Nguyen Du str., Hai Ba Trung dist., Hanoi\nWebsite: http://www.mic.gov.vn\n\nĐƠN ĐỀ NGHỊ SỬA ĐỔI, BỔ SUNG / CẤP LẠI\n\nGIẤY CHỨNG NHẬN LƯU HÀNH TỰ DO\n\nREQUEST TO REISSUE CERTIFICATE OF FREE SALE (CFS)\n\nPhần 1 Thông tin thương nhân\n\nSection 1 Firm/company/manufacturer’s Information\n\n| Tên thương nhân<br>Name of the firm/company/manufacturer | Mã số thương nhân<br>Firm/company/manufacturer code |\n| --- | --- |\n| Địa chỉ<br>Street Address | Điện thoại/fax<br>Contact Number<br>(         ) |\n|  | Thư điện tử (bắt buộc)<br>Email address (required) |\n\nĐể đáp ứng yêu cầu của nước nhập khẩu, [Tên thương nhân] đề nghị sửa đổi, bổ sung / cấp lại Giấy chứng nhận lưu hành tự do (CFS) đối với các hàng hóa như sau:\n\nTo meet the requirements of the importing country, [firm/company/manufacturer] requests to reissue CFS for the following products:\n\nPhần 2 Thông tin hàng hóa xuất khẩu đề nghị sửa đổi, bổ sung / cấp lại CFS\n\nSection 2 Product Information\n\n| STT<br>No | Tên, mô tả hàng hóa<br>(Name, description of products) | Mã số HS hàng hóa <br>(HS code) | Số và ngày cấp của CFS gốc<br>(CFS number and date issued) |\n| --- | --- | --- | --- |\n| 1 |  |  |  |\n| 2 |  |  |  |\n| 3 |  |  |  |\n\nLý do: (Đánh dấu × vào ô tương ứng)\n\nReason: (Mark × in the corresponding box)\n\n| ☐ Mất, thất lạc (lost) | ☐ Hỏng (damaged) | ☐ Có sai sót (errors) |\n| --- | --- | --- |\n\nPhần 3 Cam kết của thương nhân\n\nSection 3 Firm/company/manufacturer’s declaration\n\nTôi xin cam kết những sản phẩm này tuân thủ các quy định về tiêu chuẩn, chất lượng của Việt Nam.\n\nI declare that the kinds of products in this application comply with the standards and quality of Vietnam.\n\nTôi xin chịu mọi trách nhiệm trước pháp luật về tính xác thực của các thông tin nêu trên.\n\nI further declare that all information contained in this application form is true and correct as at the date of signing.\n\n|  | Ngày ….., tháng ….. năm 20…..<br>[Date], [Month], 20….. |\n| --- | --- |\n| Chữ ký của người đại diện theo pháp luật<br>Signature of legal representative |  |\n| Họ và tên<br>Full name |  |\n| Chức danh, vị trí việc làm<br>Your Position/title/office |  |",
    "metadata": {
        "source_file": "Maudon/PHU LUC II-TT-21-2020-TT-BTTTT.doc",
        "file_name": "PHU LUC II-TT-21-2020-TT-BTTTT.doc",
        "folder": "Maudon",
        "original_extension": ".doc",
        "cleaned_at": "2026-05-21T05:00:42"
    }
}