{
    "content": "Mẫu số 04\n\n| TÊN ĐƠN VỊ<br>...<br>------- | CỘNG HÒA XÃ HỘI CHỦ NGHĨA VIỆT NAM<br>Độc lập - Tự do - Hạnh phúc<br>--------------- |\n| --- | --- |\n\nPHIẾU ĐÁNH GIÁ, XẾP LOẠI CHẤT LƯỢNG VIÊN CHỨC\n(Giữ chức vụ lãnh đạo, quản lý)\nNăm 20...\n\n(Ban hành kèm theo Quyết định số .../QĐ-VKSTC ngày .../2021 của Viện trưởng Viện kiểm sát nhân dân tối cao)\n\n- Họ và tên: ...\n\n- Chức danh nghề nghiệp: ...\n\n- Đơn vị công tác: ...\n\nI. KẾT QUẢ TỰ ĐÁNH GIÁ\n\n1. Chính trị, tư tưởng (06 điểm)\n\n...\n\n2. Đạo đức, lối sống (06 điểm)\n\n...\n\n3. Tác phong, lề lối làm việc (06 điểm)\n\n...\n\n4. Ý thức tổ chức kỷ luật (06 điểm)\n\n...\n\n5. Thái độ phục vụ nhân dân (06 điểm)\n\n...\n\n6. Kết quả thực hiện chức trách, nhiệm vụ được giao: Nêu rõ nội dung công việc thực hiện; tỷ lệ hoàn thành, chất lượng và tiến độ công việc (từ 01 điểm đến 40 điểm)\n\n- Hoàn thành từ 100% nhiệm vụ đề ra, trong đó ít nhất 50% nhiệm vụ vượt mức trở lên: 40 điểm\n\n- Hoàn thành 100% nhiệm vụ: từ 30 điểm đến dưới 40 điểm\n\n- Các tiêu chí về kết quả thực hiện nhiệm vụ theo quy định của pháp luật, theo kế hoạch đề ra hoặc theo công việc cụ thể được giao đều hoàn thành, trong đó có không quá 20% tiêu chí chưa đảm bảo về chất lượng, tiến độ hoặc hiệu quả thấp: từ 20 điểm đến dưới 30 điểm.\n\n- Có trên 50% các tiêu chí về kết quả thực hiện nhiệm vụ theo quy định của pháp luật, theo kế hoạch đề ra hoặc theo công việc cụ thể được giao chưa bảo đảm tiến độ, chất lượng, hiệu quả: từ 01 điểm đến dưới 20 điểm.\n\n7. Kết quả hoạt động của cơ quan, đơn vị được giao lãnh đạo, quản lý, phụ trách (xác định rõ nội nội dung công việc; tỷ lệ hoàn thành, chất lượng và tiến độ công việc) (10 điểm)\n\n...\n\n8. Năng lực lãnh đạo, quản lý (05 điểm)\n\n...\n\n9. Năng lực tập hợp, đoàn kết (05 điểm)\n\n...\n\n10. Điểm cộng (tối đa 10 điểm)\n\n...\n\n11. Điểm trừ\n\n...\n\nII. TỰ NHẬN XÉT, XẾP LOẠI CHẤT LƯỢNG\n\n1. Tự nhận xét ưu, khuyết điểm\n\n...\n\n2. Tự xếp loại chất lượng\n\nViên chức tự xếp loại (đánh dấu X vào một trong 04 ô tương ứng dưới đây)\n\n|  |  |  |  |  |  |  |\n| --- | --- | --- | --- | --- | --- | --- |\n| Hoàn thành xuất sắc nhiệm vụ<br>Từ 90 đến 100 điểm |  | Hoàn thành tốt nhiệm vụ<br>Từ 80 đến dưới 90 điểm |  | Hoàn thành nhiệm vụ<br>Từ 70 đến dưới 80 điểm |  | Không hoàn thành nhiệm vụ<br>Dưới 70 điểm |\n\n|  | ..., ngày...tháng...năm<br>NGƯỜI TỰ NHẬN XÉT<br>(Ký và ghi rõ họ tên) |\n| --- | --- |\n\nIII. Ý KIẾN NHẬN XÉT, ĐÁNH GIÁ, XẾP LOẠI CỦA LÃNH ĐẠO TRỰC TIẾP QUẢN LÝ VIÊN CHỨC1\n\n1. Nhận xét, đánh giá\n\n...\n\n2. Kết quả đánh giá, xếp loại của lãnh đạo trực tiếp quản lý viên chức\n\n...\n\n|  | ..., ngày...tháng...năm...<br>NGƯỜI NHẬN XÉT<br>(Ký và ghi rõ họ tên) |\n| --- | --- |\n\nIV. KẾT QUẢ ĐÁNH GIÁ, XẾP LOẠI CHẤT LƯỢNG VIÊN CHỨC2\n\n1. Nhận xét ưu, khuyết điểm\n\n...\n\n2. Kết quả đánh giá, xếp loại chất lượng\n\n...\n\n(Hoàn thành xuất sắc nhiệm vụ; hoàn thành tốt nhiệm vụ; hoàn thành nhiệm vụ; không hoàn thành nhiệm vụ)\n\n|  | ..., ngày ... tháng... năm...<br>THỦ TRƯỞNG ĐƠN VỊ<br>(Ký, ghi rõ họ tên, đóng dấu) |\n| --- | --- |\n\n___\n\n1 Mục này dành cho lãnh đạo (quản lý) đơn vị trực tiếp đánh giá viên chức thuộc quyền.\n\n2 Mục này dành cho Thủ trưởng đơn vị cấp trên nhận xét, đánh giá đối với cấp trưởng của đơn vị trực thuộc. Đối với viên chức không giữ chức vụ lãnh đạo, quản lý, Phó Trưởng phòng (tương đương) tại các đơn vị trực thuộc VKSND tối cao, các Viện cấp cao, các VKSND cấp tỉnh, VKSND cấp huyện (có đơn vị phòng) thì Thủ trưởng đơn vị cấp trên chỉ cần ký và đóng dấu để xác nhận tính pháp lý của Phiếu. Trong trường hợp phát hiện việc đánh giá không khách quan, không đúng quy định hoặc có ý kiến khác nhau với người này thì Thủ trưởng cấp trên trực tiếp của người đánh giá quy định tại khoản 4 Điều 12 Quy chế đánh giá, phân loại công chức, viên chức, người lao động trong ngành Kiểm sát nhân dân xem xét, quyết định nhận xét, đánh giá trực tiếp vào mục này.",
    "metadata": {
        "source_file": "mauphieu/MAU SO 04-QD-323-QD-VKSTC.doc",
        "file_name": "MAU SO 04-QD-323-QD-VKSTC.doc",
        "folder": "mauphieu",
        "original_extension": ".doc",
        "cleaned_at": "2026-05-21T01:56:35"
    }
}