{
    "content": "Mẫu số 05. Phiếu yêu cầu khám chuyên khoa, cận lâm sàng\n\n| TÊN CƠ QUAN, TỔ CHỨC<br>------- | CỘNG HÒA XÃ HỘI CHỦ NGHĨA VIỆT NAM<br>Độc lập - Tự do - Hạnh phúc <br>--------------- |\n| --- | --- |\n| Số:.../…. ... | ..., ngày... tháng... năm 20... |\n\nPHIẾU YÊU CẦU KHÁM CHUYÊN KHOA/CẬN LÂM SÀNG\n\nKính gửi: ………………………………………………………………\n\nHọ và tên: …………………………………Sinh năm…………...Nam/Nữ\n\nNghề nghiệp:…………………………………………………………………….\n\nĐịa chỉ:……………………………………………………………………………\n\nChẩn đoán (nếu có): ……………………………………………………………\n\nLà đối tượng đang giám định tại:……………………..(tên cơ quan giám định).\n\nYêu cầu khám chuyên khoa/cận lâm sàng:…………………………………\n\n………………………………………………………………………………..\n\n| ...,ngày.…tháng….năm…..<br>LÃNH ĐẠO CƠ QUAN, TỔ CHỨC<br>(Ký và ghi rõ họ tên và đóng dấu) | ...,ngày.…tháng….năm…..<br>GIÁM ĐỊNH VIÊN<br>(Ký và ghi rõ họ tên) |\n| --- | --- |",
    "metadata": {
        "source_file": "mauphieu/MAU SO 05-PHU LUC IV-42-2024-TTT-BYT.doc",
        "file_name": "MAU SO 05-PHU LUC IV-42-2024-TTT-BYT.doc",
        "folder": "mauphieu",
        "original_extension": ".doc",
        "cleaned_at": "2026-05-21T01:58:54"
    }
}